rakun2/__init__.py
rakun2/class_rakun.py
rakun2/class_rakun.py~
rakun2/stopwords.json.gz
rakun2-0.31.dist-info/licenses/LICENSE
rakun2-0.31.dist-info/METADATA
rakun2-0.31.dist-info/WHEEL
rakun2-0.31.dist-info/top_level.txt
rakun2-0.31.dist-info/RECORD
