Metadata-Version: 2.4
Name: rakun2
Version: 0.31
Summary: RaKUn 2.0; Better faster stronger lighter
Home-page: http://github.com/skblaz/rakun2
Author: Blaž Škrlj
Author-email: blaz.skrlj@ijs.si
License: MIT
License-File: LICENSE
Requires-Dist: certifi>=2022.5.18.1
Requires-Dist: cycler>=0.11.0
Requires-Dist: fonttools>=4.33.3
Requires-Dist: kiwisolver>=1.4.2
Requires-Dist: matplotlib>=3.5.2
Requires-Dist: networkx>=2.8.2
Requires-Dist: numpy>=1.22.4
Requires-Dist: packaging>=21.3
Requires-Dist: Pillow>=9.1.1
Requires-Dist: pyparsing>=3.0.9
Requires-Dist: python-dateutil>=2.8.2
Requires-Dist: scipy>=1.8.1
Requires-Dist: six>=1.16.0
Requires-Dist: tqdm>=4.60
Requires-Dist: pytest>=7.1.2
Requires-Dist: pytest-sugar>=0.9.5
Requires-Dist: pymupdf>=1.21.0
Dynamic: author
Dynamic: author-email
Dynamic: home-page
Dynamic: license
Dynamic: license-file
Dynamic: requires-dist
Dynamic: summary
